{"links": {"self": {"href": "data/repositories/osrf/vrx/pullrequests/79/comments/94594728.json"}, "html": {"href": "#!/osrf/vrx/pull-requests/79/_/diff#comment-94594728"}}, "parent": {"id": 94544084, "links": {"self": {"href": "data/repositories/osrf/vrx/pullrequests/79/comments/94544084.json"}, "html": {"href": "#!/osrf/vrx/pull-requests/79/_/diff#comment-94544084"}}}, "deleted": false, "pullrequest": {"type": "pullrequest", "id": 79, "links": {"self": {"href": "data/repositories/osrf/vrx/pullrequests/79.json"}, "html": {"href": "#!/osrf/vrx/pull-requests/79"}}, "title": "Filter velodyne points issue #29"}, "content": {"raw": "Thanks Carlos,\n\nRegards,\n\nJonathan.", "markup": "markdown", "html": "<p>Thanks Carlos,</p>\n<p>Regards,</p>\n<p>Jonathan.</p>", "type": "rendered"}, "created_on": "2019-03-12T05:00:50.888927+00:00", "user": {"display_name": "Jonathan Wheare", "uuid": "{65043b9b-c505-4efe-852a-3d2393a0ee80}", "links": {"self": {"href": "https://api.bitbucket.org/2.0/users/%7B65043b9b-c505-4efe-852a-3d2393a0ee80%7D"}, "html": {"href": "https://bitbucket.org/%7B65043b9b-c505-4efe-852a-3d2393a0ee80%7D/"}, "avatar": {"href": "https://avatar-management--avatars.us-west-2.prod.public.atl-paas.net/initials/JW-2.png"}}, "nickname": "Jonathan Wheare", "type": "user", "account_id": "5b9791e8a9fd6d2c834b5864"}, "updated_on": "2019-03-12T05:00:50.936235+00:00", "type": "pullrequest_comment", "id": 94594728}