{"pagelen": 50, "values": [{"update": {"description": "Added the circle, cross and triangle symbols.\r\n\r\n* The symbols are separate white models that can be reused in the future.\r\n* All symbols are running a `gazebo_ros_color` plugin, so it\u2019s possible to change its color via a ROS message.\r\n* The placard is a new model with a white background and the three symbols. Note that the symbols are transparent, so none of them are visible by default.\r\n* There's a `symbol_controller` plugin running in each placard to allow a fix configuration \\(e.g. green circle\\) or a random configuration. This plugin also accepts a service request to create a new random configuration.\r\n\r\n![](https://bitbucket.org/repo/BgXLzgM/images/2377027615-placard.gif)\r\n*Note: This pull request is built atop of pull request #27, which should be merged first.*", "title": "Symbols and placards", "destination": {"commit": {"hash": "0ce8742bac2a", "type": "commit", "links": {"self": {"href": "data/repositories/osrf/vrx/commit/0ce8742bac2a.json"}, "html": {"href": "#!/osrf/vrx/commits/0ce8742bac2a"}}}, "repository": {"links": {"self": {"href": "data/repositories/osrf/vrx.json"}, "html": {"href": "#!/osrf/vrx"}, "avatar": {"href": "data/bytebucket.org/ravatar/{e278ca38-7edb-4e62-b785-46dff5617d98}ts=2274605"}}, "type": "repository", "name": "vrx", "full_name": "osrf/vrx", "uuid": "{e278ca38-7edb-4e62-b785-46dff5617d98}"}, "branch": {"name": "default"}}, "reason": "", "source": {"commit": {"hash": "abdebf61b1d3", "type": "commit", "links": {"self": {"href": "data/repositories/osrf/vrx/commit/abdebf61b1d3.json"}, "html": {"href": "#!/osrf/vrx/commits/abdebf61b1d3"}}}, "repository": {"links": {"self": {"href": "data/repositories/osrf/vrx.json"}, "html": {"href": "#!/osrf/vrx"}, "avatar": {"href": "data/bytebucket.org/ravatar/{e278ca38-7edb-4e62-b785-46dff5617d98}ts=2274605"}}, "type": "repository", "name": "vrx", "full_name": "osrf/vrx", "uuid": "{e278ca38-7edb-4e62-b785-46dff5617d98}"}, "branch": {"name": "placard"}}, "state": "MERGED", "author": {"display_name": "Carlos Ag\u00fcero", "uuid": "{da8a8e89-4bb0-421b-bd0e-dbbed3d4ed6a}", "links": {"self": {"href": "https://api.bitbucket.org/2.0/users/%7Bda8a8e89-4bb0-421b-bd0e-dbbed3d4ed6a%7D"}, "html": {"href": "https://bitbucket.org/%7Bda8a8e89-4bb0-421b-bd0e-dbbed3d4ed6a%7D/"}, "avatar": {"href": "data/secure.gravatar.com/avatar/692bf15758111acaddae4da15a47f9e5d=httpsavatar-management--avatars.us-west-2.prod.public.atl-paas.netinitialsCA-0.png"}}, "nickname": "caguero", "type": "user", "account_id": "557058:4ded1ddf-947e-4154-bbd1-3dba24f1bdbd"}, "date": "2018-07-26T21:58:19.663952+00:00"}, "pull_request": {"type": "pullrequest", "id": 31, "links": {"self": {"href": "data/repositories/osrf/vrx/pullrequests/31.json"}, "html": {"href": "#!/osrf/vrx/pull-requests/31"}}, "title": "Symbols and placards"}}, {"approval": {"date": "2018-07-26T21:48:19.726310+00:00", "pullrequest": {"type": "pullrequest", "id": 31, "links": {"self": {"href": "data/repositories/osrf/vrx/pullrequests/31.json"}, "html": {"href": "#!/osrf/vrx/pull-requests/31"}}, "title": "Symbols and placards"}, "user": {"display_name": "Kevin Allen", "uuid": "{29f672ad-72f4-434e-bb0e-c6f2f69974f2}", "links": {"self": {"href": "https://api.bitbucket.org/2.0/users/%7B29f672ad-72f4-434e-bb0e-c6f2f69974f2%7D"}, "html": {"href": "https://bitbucket.org/%7B29f672ad-72f4-434e-bb0e-c6f2f69974f2%7D/"}, "avatar": {"href": "data/secure.gravatar.com/avatar/355d0415f6040ffb168f44275ac2ee2fd=httpsavatar-management--avatars.us-west-2.prod.public.atl-paas.netinitialsKA-1.png"}}, "nickname": "kev-the-dev", "type": "user", "account_id": "5b04a6cf8a69f52b3ba2e5db"}}, "pull_request": {"type": "pullrequest", "id": 31, "links": {"self": {"href": "data/repositories/osrf/vrx/pullrequests/31.json"}, "html": {"href": "#!/osrf/vrx/pull-requests/31"}}, "title": "Symbols and placards"}}, {"comment": {"links": {"self": {"href": "data/repositories/osrf/vrx/pullrequests/31/comments/71193933.json"}, "html": {"href": "#!/osrf/vrx/pull-requests/31/_/diff#comment-71193933"}}, "parent": {"id": 71171884, "links": {"self": {"href": "data/repositories/osrf/vrx/pullrequests/31/comments/71171884.json"}, "html": {"href": "#!/osrf/vrx/pull-requests/31/_/diff#comment-71171884"}}}, "deleted": false, "pullrequest": {"type": "pullrequest", "id": 31, "links": {"self": {"href": "data/repositories/osrf/vrx/pullrequests/31.json"}, "html": {"href": "#!/osrf/vrx/pull-requests/31"}}, "title": "Symbols and placards"}, "content": {"raw": "Done in [abdebf6](#!/osrf/vmrc/commits/abdebf61b1d3597988fa5ddd85d67fc4296f4ae8?at=default). There's room for improve the way `dock_2016/model.sdf` and `dock_2018/model.sdf` are created with some templating but I ran out of time.", "markup": "markdown", "html": "<p>Done in <a data-is-external-link=\"true\" href=\"#!/osrf/vmrc/commits/abdebf61b1d3597988fa5ddd85d67fc4296f4ae8?at=default\" rel=\"nofollow\">abdebf6</a>. There's room for improve the way <code>dock_2016/model.sdf</code> and <code>dock_2018/model.sdf</code> are created with some templating but I ran out of time.</p>", "type": "rendered"}, "created_on": "2018-07-26T21:16:15.169353+00:00", "user": {"display_name": "Carlos Ag\u00fcero", "uuid": "{da8a8e89-4bb0-421b-bd0e-dbbed3d4ed6a}", "links": {"self": {"href": "https://api.bitbucket.org/2.0/users/%7Bda8a8e89-4bb0-421b-bd0e-dbbed3d4ed6a%7D"}, "html": {"href": "https://bitbucket.org/%7Bda8a8e89-4bb0-421b-bd0e-dbbed3d4ed6a%7D/"}, "avatar": {"href": "data/secure.gravatar.com/avatar/692bf15758111acaddae4da15a47f9e5d=httpsavatar-management--avatars.us-west-2.prod.public.atl-paas.netinitialsCA-0.png"}}, "nickname": "caguero", "type": "user", "account_id": "557058:4ded1ddf-947e-4154-bbd1-3dba24f1bdbd"}, "inline": {}, "updated_on": "2018-07-26T21:16:15.175118+00:00", "type": "pullrequest_comment", "id": 71193933}, "pull_request": {"type": "pullrequest", "id": 31, "links": {"self": {"href": "data/repositories/osrf/vrx/pullrequests/31.json"}, "html": {"href": "#!/osrf/vrx/pull-requests/31"}}, "title": "Symbols and placards"}}, {"update": {"description": "Added the circle, cross and triangle symbols.\r\n\r\n* The symbols are separate white models that can be reused in the future.\r\n* All symbols are running a `gazebo_ros_color` plugin, so it\u2019s possible to change its color via a ROS message.\r\n* The placard is a new model with a white background and the three symbols. Note that the symbols are transparent, so none of them are visible by default.\r\n* There's a `symbol_controller` plugin running in each placard to allow a fix configuration \\(e.g. green circle\\) or a random configuration. This plugin also accepts a service request to create a new random configuration.\r\n\r\n![](https://bitbucket.org/repo/BgXLzgM/images/2377027615-placard.gif)\r\n*Note: This pull request is built atop of pull request #27, which should be merged first.*", "title": "Symbols and placards", "destination": {"commit": {"hash": "0ce8742bac2a", "type": "commit", "links": {"self": {"href": "data/repositories/osrf/vrx/commit/0ce8742bac2a.json"}, "html": {"href": "#!/osrf/vrx/commits/0ce8742bac2a"}}}, "repository": {"links": {"self": {"href": "data/repositories/osrf/vrx.json"}, "html": {"href": "#!/osrf/vrx"}, "avatar": {"href": "data/bytebucket.org/ravatar/{e278ca38-7edb-4e62-b785-46dff5617d98}ts=2274605"}}, "type": "repository", "name": "vrx", "full_name": "osrf/vrx", "uuid": "{e278ca38-7edb-4e62-b785-46dff5617d98}"}, "branch": {"name": "default"}}, "reason": "", "source": {"commit": {"hash": "abdebf61b1d3", "type": "commit", "links": {"self": {"href": "data/repositories/osrf/vrx/commit/abdebf61b1d3.json"}, "html": {"href": "#!/osrf/vrx/commits/abdebf61b1d3"}}}, "repository": {"links": {"self": {"href": "data/repositories/osrf/vrx.json"}, "html": {"href": "#!/osrf/vrx"}, "avatar": {"href": "data/bytebucket.org/ravatar/{e278ca38-7edb-4e62-b785-46dff5617d98}ts=2274605"}}, "type": "repository", "name": "vrx", "full_name": "osrf/vrx", "uuid": "{e278ca38-7edb-4e62-b785-46dff5617d98}"}, "branch": {"name": "placard"}}, "state": "OPEN", "author": {"display_name": "Carlos Ag\u00fcero", "uuid": "{da8a8e89-4bb0-421b-bd0e-dbbed3d4ed6a}", "links": {"self": {"href": "https://api.bitbucket.org/2.0/users/%7Bda8a8e89-4bb0-421b-bd0e-dbbed3d4ed6a%7D"}, "html": {"href": "https://bitbucket.org/%7Bda8a8e89-4bb0-421b-bd0e-dbbed3d4ed6a%7D/"}, "avatar": {"href": "data/secure.gravatar.com/avatar/692bf15758111acaddae4da15a47f9e5d=httpsavatar-management--avatars.us-west-2.prod.public.atl-paas.netinitialsCA-0.png"}}, "nickname": "caguero", "type": "user", "account_id": "557058:4ded1ddf-947e-4154-bbd1-3dba24f1bdbd"}, "date": "2018-07-26T21:13:38.266890+00:00"}, "pull_request": {"type": "pullrequest", "id": 31, "links": {"self": {"href": "data/repositories/osrf/vrx/pullrequests/31.json"}, "html": {"href": "#!/osrf/vrx/pull-requests/31"}}, "title": "Symbols and placards"}}, {"comment": {"links": {"self": {"href": "data/repositories/osrf/vrx/pullrequests/31/comments/71173611.json"}, "html": {"href": "#!/osrf/vrx/pull-requests/31/_/diff#comment-71173611"}}, "parent": {"id": 71171988, "links": {"self": {"href": "data/repositories/osrf/vrx/pullrequests/31/comments/71171988.json"}, "html": {"href": "#!/osrf/vrx/pull-requests/31/_/diff#comment-71171988"}}}, "deleted": false, "pullrequest": {"type": "pullrequest", "id": 31, "links": {"self": {"href": "data/repositories/osrf/vrx/pullrequests/31.json"}, "html": {"href": "#!/osrf/vrx/pull-requests/31"}}, "title": "Symbols and placards"}, "content": {"raw": "Ah didn\u2019t see, nevermind", "markup": "markdown", "html": "<p>Ah didn\u2019t see, nevermind</p>", "type": "rendered"}, "created_on": "2018-07-26T17:21:01.771027+00:00", "user": {"display_name": "Kevin Allen", "uuid": "{29f672ad-72f4-434e-bb0e-c6f2f69974f2}", "links": {"self": {"href": "https://api.bitbucket.org/2.0/users/%7B29f672ad-72f4-434e-bb0e-c6f2f69974f2%7D"}, "html": {"href": "https://bitbucket.org/%7B29f672ad-72f4-434e-bb0e-c6f2f69974f2%7D/"}, "avatar": {"href": "data/secure.gravatar.com/avatar/355d0415f6040ffb168f44275ac2ee2fd=httpsavatar-management--avatars.us-west-2.prod.public.atl-paas.netinitialsKA-1.png"}}, "nickname": "kev-the-dev", "type": "user", "account_id": "5b04a6cf8a69f52b3ba2e5db"}, "inline": {}, "updated_on": "2018-07-26T17:21:01.779595+00:00", "type": "pullrequest_comment", "id": 71173611}, "pull_request": {"type": "pullrequest", "id": 31, "links": {"self": {"href": "data/repositories/osrf/vrx/pullrequests/31.json"}, "html": {"href": "#!/osrf/vrx/pull-requests/31"}}, "title": "Symbols and placards"}}, {"comment": {"links": {"self": {"href": "data/repositories/osrf/vrx/pullrequests/31/comments/71171988.json"}, "html": {"href": "#!/osrf/vrx/pull-requests/31/_/diff#comment-71171988"}}, "parent": {"id": 71171670, "links": {"self": {"href": "data/repositories/osrf/vrx/pullrequests/31/comments/71171670.json"}, "html": {"href": "#!/osrf/vrx/pull-requests/31/_/diff#comment-71171670"}}}, "deleted": false, "pullrequest": {"type": "pullrequest", "id": 31, "links": {"self": {"href": "data/repositories/osrf/vrx/pullrequests/31.json"}, "html": {"href": "#!/osrf/vrx/pull-requests/31"}}, "title": "Symbols and placards"}, "content": {"raw": "Is this an issue? It\u2019s in lines 11-13.", "markup": "markdown", "html": "<p>Is this an issue? It\u2019s in lines 11-13.</p>", "type": "rendered"}, "created_on": "2018-07-26T17:04:02.867927+00:00", "user": {"display_name": "Carlos Ag\u00fcero", "uuid": "{da8a8e89-4bb0-421b-bd0e-dbbed3d4ed6a}", "links": {"self": {"href": "https://api.bitbucket.org/2.0/users/%7Bda8a8e89-4bb0-421b-bd0e-dbbed3d4ed6a%7D"}, "html": {"href": "https://bitbucket.org/%7Bda8a8e89-4bb0-421b-bd0e-dbbed3d4ed6a%7D/"}, "avatar": {"href": "data/secure.gravatar.com/avatar/692bf15758111acaddae4da15a47f9e5d=httpsavatar-management--avatars.us-west-2.prod.public.atl-paas.netinitialsCA-0.png"}}, "nickname": "caguero", "type": "user", "account_id": "557058:4ded1ddf-947e-4154-bbd1-3dba24f1bdbd"}, "inline": {}, "updated_on": "2018-07-26T17:04:02.883132+00:00", "type": "pullrequest_comment", "id": 71171988}, "pull_request": {"type": "pullrequest", "id": 31, "links": {"self": {"href": "data/repositories/osrf/vrx/pullrequests/31.json"}, "html": {"href": "#!/osrf/vrx/pull-requests/31"}}, "title": "Symbols and placards"}}, {"comment": {"links": {"self": {"href": "data/repositories/osrf/vrx/pullrequests/31/comments/71171884.json"}, "html": {"href": "#!/osrf/vrx/pull-requests/31/_/diff#comment-71171884"}}, "deleted": false, "pullrequest": {"type": "pullrequest", "id": 31, "links": {"self": {"href": "data/repositories/osrf/vrx/pullrequests/31.json"}, "html": {"href": "#!/osrf/vrx/pull-requests/31"}}, "title": "Symbols and placards"}, "content": {"raw": "Suggestion: change the dock\\_2016 model to dock\\_2016\\_base and make dock\\_2016 contain the placards already \\(same for 2018\\). I think that would be cleaner as most users will assume the dock contains the placard already \\(it was always there for the competition\\)", "markup": "markdown", "html": "<p>Suggestion: change the dock_2016 model to dock_2016_base and make dock_2016 contain the placards already (same for 2018). I think that would be cleaner as most users will assume the dock contains the placard already (it was always there for the competition)</p>", "type": "rendered"}, "created_on": "2018-07-26T17:02:55.526723+00:00", "user": {"display_name": "Kevin Allen", "uuid": "{29f672ad-72f4-434e-bb0e-c6f2f69974f2}", "links": {"self": {"href": "https://api.bitbucket.org/2.0/users/%7B29f672ad-72f4-434e-bb0e-c6f2f69974f2%7D"}, "html": {"href": "https://bitbucket.org/%7B29f672ad-72f4-434e-bb0e-c6f2f69974f2%7D/"}, "avatar": {"href": "data/secure.gravatar.com/avatar/355d0415f6040ffb168f44275ac2ee2fd=httpsavatar-management--avatars.us-west-2.prod.public.atl-paas.netinitialsKA-1.png"}}, "nickname": "kev-the-dev", "type": "user", "account_id": "5b04a6cf8a69f52b3ba2e5db"}, "inline": {}, "updated_on": "2018-07-26T17:02:55.534519+00:00", "type": "pullrequest_comment", "id": 71171884}, "pull_request": {"type": "pullrequest", "id": 31, "links": {"self": {"href": "data/repositories/osrf/vrx/pullrequests/31.json"}, "html": {"href": "#!/osrf/vrx/pull-requests/31"}}, "title": "Symbols and placards"}}, {"comment": {"links": {"self": {"href": "data/repositories/osrf/vrx/pullrequests/31/comments/71171670.json"}, "html": {"href": "#!/osrf/vrx/pull-requests/31/_/diff#comment-71171670"}}, "deleted": false, "pullrequest": {"type": "pullrequest", "id": 31, "links": {"self": {"href": "data/repositories/osrf/vrx/pullrequests/31.json"}, "html": {"href": "#!/osrf/vrx/pull-requests/31"}}, "title": "Symbols and placards"}, "content": {"raw": "Issue with merge?", "markup": "markdown", "html": "<p>Issue with merge?</p>", "type": "rendered"}, "created_on": "2018-07-26T17:00:45.371491+00:00", "user": {"display_name": "Kevin Allen", "uuid": "{29f672ad-72f4-434e-bb0e-c6f2f69974f2}", "links": {"self": {"href": "https://api.bitbucket.org/2.0/users/%7B29f672ad-72f4-434e-bb0e-c6f2f69974f2%7D"}, "html": {"href": "https://bitbucket.org/%7B29f672ad-72f4-434e-bb0e-c6f2f69974f2%7D/"}, "avatar": {"href": "data/secure.gravatar.com/avatar/355d0415f6040ffb168f44275ac2ee2fd=httpsavatar-management--avatars.us-west-2.prod.public.atl-paas.netinitialsKA-1.png"}}, "nickname": "kev-the-dev", "type": "user", "account_id": "5b04a6cf8a69f52b3ba2e5db"}, "inline": {}, "updated_on": "2018-07-26T17:00:45.378727+00:00", "type": "pullrequest_comment", "id": 71171670}, "pull_request": {"type": "pullrequest", "id": 31, "links": {"self": {"href": "data/repositories/osrf/vrx/pullrequests/31.json"}, "html": {"href": "#!/osrf/vrx/pull-requests/31"}}, "title": "Symbols and placards"}}, {"update": {"description": "Added the circle, cross and triangle symbols.\r\n\r\n* The symbols are separate white models that can be reused in the future.\r\n* All symbols are running a `gazebo_ros_color` plugin, so it\u2019s possible to change its color via a ROS message.\r\n* The placard is a new model with a white background and the three symbols. Note that the symbols are transparent, so none of them are visible by default.\r\n* There's a `symbol_controller` plugin running in each placard to allow a fix configuration \\(e.g. green circle\\) or a random configuration. This plugin also accepts a service request to create a new random configuration.\r\n\r\n![](https://bitbucket.org/repo/BgXLzgM/images/2377027615-placard.gif)\r\n*Note: This pull request is built atop of pull request #27, which should be merged first.*", "title": "Symbols and placards", "destination": {"commit": {"hash": "0ce8742bac2a", "type": "commit", "links": {"self": {"href": "data/repositories/osrf/vrx/commit/0ce8742bac2a.json"}, "html": {"href": "#!/osrf/vrx/commits/0ce8742bac2a"}}}, "repository": {"links": {"self": {"href": "data/repositories/osrf/vrx.json"}, "html": {"href": "#!/osrf/vrx"}, "avatar": {"href": "data/bytebucket.org/ravatar/{e278ca38-7edb-4e62-b785-46dff5617d98}ts=2274605"}}, "type": "repository", "name": "vrx", "full_name": "osrf/vrx", "uuid": "{e278ca38-7edb-4e62-b785-46dff5617d98}"}, "branch": {"name": "default"}}, "reason": "", "source": {"commit": {"hash": "ecd19338bc8c", "type": "commit", "links": {"self": {"href": "data/repositories/osrf/vrx/commit/ecd19338bc8c.json"}, "html": {"href": "#!/osrf/vrx/commits/ecd19338bc8c"}}}, "repository": {"links": {"self": {"href": "data/repositories/osrf/vrx.json"}, "html": {"href": "#!/osrf/vrx"}, "avatar": {"href": "data/bytebucket.org/ravatar/{e278ca38-7edb-4e62-b785-46dff5617d98}ts=2274605"}}, "type": "repository", "name": "vrx", "full_name": "osrf/vrx", "uuid": "{e278ca38-7edb-4e62-b785-46dff5617d98}"}, "branch": {"name": "placard"}}, "state": "OPEN", "author": {"display_name": "Carlos Ag\u00fcero", "uuid": "{da8a8e89-4bb0-421b-bd0e-dbbed3d4ed6a}", "links": {"self": {"href": "https://api.bitbucket.org/2.0/users/%7Bda8a8e89-4bb0-421b-bd0e-dbbed3d4ed6a%7D"}, "html": {"href": "https://bitbucket.org/%7Bda8a8e89-4bb0-421b-bd0e-dbbed3d4ed6a%7D/"}, "avatar": {"href": "data/secure.gravatar.com/avatar/692bf15758111acaddae4da15a47f9e5d=httpsavatar-management--avatars.us-west-2.prod.public.atl-paas.netinitialsCA-0.png"}}, "nickname": "caguero", "type": "user", "account_id": "557058:4ded1ddf-947e-4154-bbd1-3dba24f1bdbd"}, "date": "2018-07-26T16:49:51.866871+00:00"}, "pull_request": {"type": "pullrequest", "id": 31, "links": {"self": {"href": "data/repositories/osrf/vrx/pullrequests/31.json"}, "html": {"href": "#!/osrf/vrx/pull-requests/31"}}, "title": "Symbols and placards"}}, {"update": {"description": "Added the circle, cross and triangle symbols.\r\n\r\n* The symbols are separate white models that can be reused in the future.\r\n* All symbols are running a `gazebo_ros_color` plugin, so it\u2019s possible to change its color via a ROS message.\r\n* The placard is a new model with a white background and the three symbols. Note that the symbols are transparent, so none of them are visible by default.\r\n* There's a `symbol_controller` plugin running in each placard to allow a fix configuration \\(e.g. green circle\\) or a random configuration. This plugin also accepts a service request to create a new random configuration.\r\n\r\n![](https://bitbucket.org/repo/BgXLzgM/images/2377027615-placard.gif)\r\n*Note: This pull request is built atop of pull request #27, which should be merged first.*", "title": "Symbols and placards", "destination": {"commit": {"hash": "0ce8742bac2a", "type": "commit", "links": {"self": {"href": "data/repositories/osrf/vrx/commit/0ce8742bac2a.json"}, "html": {"href": "#!/osrf/vrx/commits/0ce8742bac2a"}}}, "repository": {"links": {"self": {"href": "data/repositories/osrf/vrx.json"}, "html": {"href": "#!/osrf/vrx"}, "avatar": {"href": "data/bytebucket.org/ravatar/{e278ca38-7edb-4e62-b785-46dff5617d98}ts=2274605"}}, "type": "repository", "name": "vrx", "full_name": "osrf/vrx", "uuid": "{e278ca38-7edb-4e62-b785-46dff5617d98}"}, "branch": {"name": "default"}}, "reason": "", "source": {"commit": {"hash": "ecd19338bc8c", "type": "commit", "links": {"self": {"href": "data/repositories/osrf/vrx/commit/ecd19338bc8c.json"}, "html": {"href": "#!/osrf/vrx/commits/ecd19338bc8c"}}}, "repository": {"links": {"self": {"href": "data/repositories/osrf/vrx.json"}, "html": {"href": "#!/osrf/vrx"}, "avatar": {"href": "data/bytebucket.org/ravatar/{e278ca38-7edb-4e62-b785-46dff5617d98}ts=2274605"}}, "type": "repository", "name": "vrx", "full_name": "osrf/vrx", "uuid": "{e278ca38-7edb-4e62-b785-46dff5617d98}"}, "branch": {"name": "placard"}}, "state": "OPEN", "author": {"display_name": "Carlos Ag\u00fcero", "uuid": "{da8a8e89-4bb0-421b-bd0e-dbbed3d4ed6a}", "links": {"self": {"href": "https://api.bitbucket.org/2.0/users/%7Bda8a8e89-4bb0-421b-bd0e-dbbed3d4ed6a%7D"}, "html": {"href": "https://bitbucket.org/%7Bda8a8e89-4bb0-421b-bd0e-dbbed3d4ed6a%7D/"}, "avatar": {"href": "data/secure.gravatar.com/avatar/692bf15758111acaddae4da15a47f9e5d=httpsavatar-management--avatars.us-west-2.prod.public.atl-paas.netinitialsCA-0.png"}}, "nickname": "caguero", "type": "user", "account_id": "557058:4ded1ddf-947e-4154-bbd1-3dba24f1bdbd"}, "date": "2018-07-26T16:49:51.543274+00:00"}, "pull_request": {"type": "pullrequest", "id": 31, "links": {"self": {"href": "data/repositories/osrf/vrx/pullrequests/31.json"}, "html": {"href": "#!/osrf/vrx/pull-requests/31"}}, "title": "Symbols and placards"}}, {"update": {"description": "Added the circle, cross and triangle symbols.\r\n\r\n* The symbols are separate white models that can be reused in the future.\r\n* All symbols are running a `gazebo_ros_color` plugin, so it\u2019s possible to change its color via a ROS message.\r\n* The placard is a new model with a white background and the three symbols. Note that the symbols are transparent, so none of them are visible by default.\r\n* There's a `symbol_controller` plugin running in each placard to allow a fix configuration \\(e.g. green circle\\) or a random configuration. This plugin also accepts a service request to create a new random configuration.\r\n\r\n![](https://bitbucket.org/repo/BgXLzgM/images/2377027615-placard.gif)\r\n*Note: This pull request is built atop of pull request #27, which should be merged first.*", "title": "Symbols and placards", "destination": {"commit": {"hash": "2e7234c8d8b3", "type": "commit", "links": {"self": {"href": "data/repositories/osrf/vrx/commit/2e7234c8d8b3.json"}, "html": {"href": "#!/osrf/vrx/commits/2e7234c8d8b3"}}}, "repository": {"links": {"self": {"href": "data/repositories/osrf/vrx.json"}, "html": {"href": "#!/osrf/vrx"}, "avatar": {"href": "data/bytebucket.org/ravatar/{e278ca38-7edb-4e62-b785-46dff5617d98}ts=2274605"}}, "type": "repository", "name": "vrx", "full_name": "osrf/vrx", "uuid": "{e278ca38-7edb-4e62-b785-46dff5617d98}"}, "branch": {"name": "default"}}, "reason": "", "source": {"commit": {"hash": "ecd19338bc8c", "type": "commit", "links": {"self": {"href": "data/repositories/osrf/vrx/commit/ecd19338bc8c.json"}, "html": {"href": "#!/osrf/vrx/commits/ecd19338bc8c"}}}, "repository": {"links": {"self": {"href": "data/repositories/osrf/vrx.json"}, "html": {"href": "#!/osrf/vrx"}, "avatar": {"href": "data/bytebucket.org/ravatar/{e278ca38-7edb-4e62-b785-46dff5617d98}ts=2274605"}}, "type": "repository", "name": "vrx", "full_name": "osrf/vrx", "uuid": "{e278ca38-7edb-4e62-b785-46dff5617d98}"}, "branch": {"name": "placard"}}, "state": "OPEN", "author": {"display_name": "Carlos Ag\u00fcero", "uuid": "{da8a8e89-4bb0-421b-bd0e-dbbed3d4ed6a}", "links": {"self": {"href": "https://api.bitbucket.org/2.0/users/%7Bda8a8e89-4bb0-421b-bd0e-dbbed3d4ed6a%7D"}, "html": {"href": "https://bitbucket.org/%7Bda8a8e89-4bb0-421b-bd0e-dbbed3d4ed6a%7D/"}, "avatar": {"href": "data/secure.gravatar.com/avatar/692bf15758111acaddae4da15a47f9e5d=httpsavatar-management--avatars.us-west-2.prod.public.atl-paas.netinitialsCA-0.png"}}, "nickname": "caguero", "type": "user", "account_id": "557058:4ded1ddf-947e-4154-bbd1-3dba24f1bdbd"}, "date": "2018-07-26T16:26:17.795878+00:00"}, "pull_request": {"type": "pullrequest", "id": 31, "links": {"self": {"href": "data/repositories/osrf/vrx/pullrequests/31.json"}, "html": {"href": "#!/osrf/vrx/pull-requests/31"}}, "title": "Symbols and placards"}}, {"update": {"description": "Added the circle, cross and triangle symbols.\r\n\r\n* The symbols are separate white models that can be reused in the future.\r\n* All symbols are running a `gazebo_ros_color` plugin, so it\u2019s possible to change its color via a ROS message.\r\n* The placard is a new model with a white background and the three symbols. Note that the symbols are transparent, so none of them are visible by default.\r\n* There's a `symbol_controller` plugin running in each placard to allow a fix configuration \\(e.g. green circle\\) or a random configuration. This plugin also accepts a service request to create a new random configuration.\r\n\r\n![](https://bitbucket.org/repo/BgXLzgM/images/2377027615-placard.gif)\r\n*Note: This pull request is built atop of pull request #27, which should be merged first.*", "title": "Symbols and placards", "destination": {"commit": {"hash": "2e7234c8d8b3", "type": "commit", "links": {"self": {"href": "data/repositories/osrf/vrx/commit/2e7234c8d8b3.json"}, "html": {"href": "#!/osrf/vrx/commits/2e7234c8d8b3"}}}, "repository": {"links": {"self": {"href": "data/repositories/osrf/vrx.json"}, "html": {"href": "#!/osrf/vrx"}, "avatar": {"href": "data/bytebucket.org/ravatar/{e278ca38-7edb-4e62-b785-46dff5617d98}ts=2274605"}}, "type": "repository", "name": "vrx", "full_name": "osrf/vrx", "uuid": "{e278ca38-7edb-4e62-b785-46dff5617d98}"}, "branch": {"name": "default"}}, "reason": "", "source": {"commit": {"hash": "f275393766ba", "type": "commit", "links": {"self": {"href": "data/repositories/osrf/vrx/commit/f275393766ba.json"}, "html": {"href": "#!/osrf/vrx/commits/f275393766ba"}}}, "repository": {"links": {"self": {"href": "data/repositories/osrf/vrx.json"}, "html": {"href": "#!/osrf/vrx"}, "avatar": {"href": "data/bytebucket.org/ravatar/{e278ca38-7edb-4e62-b785-46dff5617d98}ts=2274605"}}, "type": "repository", "name": "vrx", "full_name": "osrf/vrx", "uuid": "{e278ca38-7edb-4e62-b785-46dff5617d98}"}, "branch": {"name": "placard"}}, "state": "OPEN", "author": {"display_name": "Carlos Ag\u00fcero", "uuid": "{da8a8e89-4bb0-421b-bd0e-dbbed3d4ed6a}", "links": {"self": {"href": "https://api.bitbucket.org/2.0/users/%7Bda8a8e89-4bb0-421b-bd0e-dbbed3d4ed6a%7D"}, "html": {"href": "https://bitbucket.org/%7Bda8a8e89-4bb0-421b-bd0e-dbbed3d4ed6a%7D/"}, "avatar": {"href": "data/secure.gravatar.com/avatar/692bf15758111acaddae4da15a47f9e5d=httpsavatar-management--avatars.us-west-2.prod.public.atl-paas.netinitialsCA-0.png"}}, "nickname": "caguero", "type": "user", "account_id": "557058:4ded1ddf-947e-4154-bbd1-3dba24f1bdbd"}, "date": "2018-07-26T16:13:09.397354+00:00"}, "pull_request": {"type": "pullrequest", "id": 31, "links": {"self": {"href": "data/repositories/osrf/vrx/pullrequests/31.json"}, "html": {"href": "#!/osrf/vrx/pull-requests/31"}}, "title": "Symbols and placards"}}, {"update": {"description": "Added the circle, cross and triangle symbols.\r\n\r\n* The symbols are separate white models that can be reused in the future.\r\n* All symbols are running a `gazebo_ros_color` plugin, so it\u2019s possible to change its color via a ROS message.\r\n* The placard is a new model with a white background and the three symbols. Note that the symbols are transparent, so none of them are visible by default.\r\n* There's a `symbol_controller` plugin running in each placard to allow a fix configuration \\(e.g. green circle\\) or a random configuration. This plugin also accepts a service request to create a new random configuration.\r\n\r\n![](https://bitbucket.org/repo/BgXLzgM/images/2377027615-placard.gif)\r\n*Note: This pull request is built atop of pull request #27, which should be merged first.*", "title": "Symbols and placards", "destination": {"commit": {"hash": "24481763302f", "type": "commit", "links": {"self": {"href": "data/repositories/osrf/vrx/commit/24481763302f.json"}, "html": {"href": "#!/osrf/vrx/commits/24481763302f"}}}, "repository": {"links": {"self": {"href": "data/repositories/osrf/vrx.json"}, "html": {"href": "#!/osrf/vrx"}, "avatar": {"href": "data/bytebucket.org/ravatar/{e278ca38-7edb-4e62-b785-46dff5617d98}ts=2274605"}}, "type": "repository", "name": "vrx", "full_name": "osrf/vrx", "uuid": "{e278ca38-7edb-4e62-b785-46dff5617d98}"}, "branch": {"name": "default"}}, "reason": "", "source": {"commit": {"hash": "d51252c16e43", "type": "commit", "links": {"self": {"href": "data/repositories/osrf/vrx/commit/d51252c16e43.json"}, "html": {"href": "#!/osrf/vrx/commits/d51252c16e43"}}}, "repository": {"links": {"self": {"href": "data/repositories/osrf/vrx.json"}, "html": {"href": "#!/osrf/vrx"}, "avatar": {"href": "data/bytebucket.org/ravatar/{e278ca38-7edb-4e62-b785-46dff5617d98}ts=2274605"}}, "type": "repository", "name": "vrx", "full_name": "osrf/vrx", "uuid": "{e278ca38-7edb-4e62-b785-46dff5617d98}"}, "branch": {"name": "placard"}}, "state": "OPEN", "author": {"display_name": "Carlos Ag\u00fcero", "uuid": "{da8a8e89-4bb0-421b-bd0e-dbbed3d4ed6a}", "links": {"self": {"href": "https://api.bitbucket.org/2.0/users/%7Bda8a8e89-4bb0-421b-bd0e-dbbed3d4ed6a%7D"}, "html": {"href": "https://bitbucket.org/%7Bda8a8e89-4bb0-421b-bd0e-dbbed3d4ed6a%7D/"}, "avatar": {"href": "data/secure.gravatar.com/avatar/692bf15758111acaddae4da15a47f9e5d=httpsavatar-management--avatars.us-west-2.prod.public.atl-paas.netinitialsCA-0.png"}}, "nickname": "caguero", "type": "user", "account_id": "557058:4ded1ddf-947e-4154-bbd1-3dba24f1bdbd"}, "date": "2018-07-26T15:35:31.928971+00:00"}, "pull_request": {"type": "pullrequest", "id": 31, "links": {"self": {"href": "data/repositories/osrf/vrx/pullrequests/31.json"}, "html": {"href": "#!/osrf/vrx/pull-requests/31"}}, "title": "Symbols and placards"}}, {"update": {"description": "Added the circle, cross and triangle symbols.\r\n\r\n* The symbols are separate white models that can be reused in the future.\r\n* All symbols are running a `gazebo_ros_color` plugin, so it\u2019s possible to change its color via a ROS message.\r\n* The placard is a new model with a white background and the three symbols. Note that the symbols are transparent, so none of them are visible by default.\r\n* There's a `symbol_controller` plugin running in each placard to allow a fix configuration \\(e.g. green circle\\) or a random configuration. This plugin also accepts a service request to create a new random configuration.\r\n\r\n![](https://bitbucket.org/repo/BgXLzgM/images/2377027615-placard.gif)\r\n*Note: This pull request is built atop of pull request #27, which should be merged first.*", "title": "Symbols and placards", "destination": {"commit": {"hash": "24481763302f", "type": "commit", "links": {"self": {"href": "data/repositories/osrf/vrx/commit/24481763302f.json"}, "html": {"href": "#!/osrf/vrx/commits/24481763302f"}}}, "repository": {"links": {"self": {"href": "data/repositories/osrf/vrx.json"}, "html": {"href": "#!/osrf/vrx"}, "avatar": {"href": "data/bytebucket.org/ravatar/{e278ca38-7edb-4e62-b785-46dff5617d98}ts=2274605"}}, "type": "repository", "name": "vrx", "full_name": "osrf/vrx", "uuid": "{e278ca38-7edb-4e62-b785-46dff5617d98}"}, "branch": {"name": "default"}}, "reason": "", "source": {"commit": {"hash": "7432c24d0962", "type": "commit", "links": {"self": {"href": "data/repositories/osrf/vrx/commit/7432c24d0962.json"}, "html": {"href": "#!/osrf/vrx/commits/7432c24d0962"}}}, "repository": {"links": {"self": {"href": "data/repositories/osrf/vrx.json"}, "html": {"href": "#!/osrf/vrx"}, "avatar": {"href": "data/bytebucket.org/ravatar/{e278ca38-7edb-4e62-b785-46dff5617d98}ts=2274605"}}, "type": "repository", "name": "vrx", "full_name": "osrf/vrx", "uuid": "{e278ca38-7edb-4e62-b785-46dff5617d98}"}, "branch": {"name": "placard"}}, "state": "OPEN", "author": {"display_name": "Carlos Ag\u00fcero", "uuid": "{da8a8e89-4bb0-421b-bd0e-dbbed3d4ed6a}", "links": {"self": {"href": "https://api.bitbucket.org/2.0/users/%7Bda8a8e89-4bb0-421b-bd0e-dbbed3d4ed6a%7D"}, "html": {"href": "https://bitbucket.org/%7Bda8a8e89-4bb0-421b-bd0e-dbbed3d4ed6a%7D/"}, "avatar": {"href": "data/secure.gravatar.com/avatar/692bf15758111acaddae4da15a47f9e5d=httpsavatar-management--avatars.us-west-2.prod.public.atl-paas.netinitialsCA-0.png"}}, "nickname": "caguero", "type": "user", "account_id": "557058:4ded1ddf-947e-4154-bbd1-3dba24f1bdbd"}, "date": "2018-07-26T15:33:44.127688+00:00"}, "pull_request": {"type": "pullrequest", "id": 31, "links": {"self": {"href": "data/repositories/osrf/vrx/pullrequests/31.json"}, "html": {"href": "#!/osrf/vrx/pull-requests/31"}}, "title": "Symbols and placards"}}, {"comment": {"links": {"self": {"href": "data/repositories/osrf/vrx/pullrequests/31/comments/71072518.json"}, "html": {"href": "#!/osrf/vrx/pull-requests/31/_/diff#comment-71072518"}}, "parent": {"id": 71070931, "links": {"self": {"href": "data/repositories/osrf/vrx/pullrequests/31/comments/71070931.json"}, "html": {"href": "#!/osrf/vrx/pull-requests/31/_/diff#comment-71070931"}}}, "deleted": false, "pullrequest": {"type": "pullrequest", "id": 31, "links": {"self": {"href": "data/repositories/osrf/vrx/pullrequests/31.json"}, "html": {"href": "#!/osrf/vrx/pull-requests/31"}}, "title": "Symbols and placards"}, "content": {"raw": "Tweaked in [7432c24](#!/osrf/vmrc/commits/7432c24d09627dec62c9681b56b6f11d1d03cc22)\u00a0. Thanks!", "markup": "markdown", "html": "<p>Tweaked in <a data-is-external-link=\"true\" href=\"#!/osrf/vmrc/commits/7432c24d09627dec62c9681b56b6f11d1d03cc22\" rel=\"nofollow\">7432c24</a>\u00a0. Thanks!</p>", "type": "rendered"}, "created_on": "2018-07-26T01:29:58.730002+00:00", "user": {"display_name": "Carlos Ag\u00fcero", "uuid": "{da8a8e89-4bb0-421b-bd0e-dbbed3d4ed6a}", "links": {"self": {"href": "https://api.bitbucket.org/2.0/users/%7Bda8a8e89-4bb0-421b-bd0e-dbbed3d4ed6a%7D"}, "html": {"href": "https://bitbucket.org/%7Bda8a8e89-4bb0-421b-bd0e-dbbed3d4ed6a%7D/"}, "avatar": {"href": "data/secure.gravatar.com/avatar/692bf15758111acaddae4da15a47f9e5d=httpsavatar-management--avatars.us-west-2.prod.public.atl-paas.netinitialsCA-0.png"}}, "nickname": "caguero", "type": "user", "account_id": "557058:4ded1ddf-947e-4154-bbd1-3dba24f1bdbd"}, "inline": {}, "updated_on": "2018-07-26T01:29:58.738247+00:00", "type": "pullrequest_comment", "id": 71072518}, "pull_request": {"type": "pullrequest", "id": 31, "links": {"self": {"href": "data/repositories/osrf/vrx/pullrequests/31.json"}, "html": {"href": "#!/osrf/vrx/pull-requests/31"}}, "title": "Symbols and placards"}}, {"update": {"description": "Added the circle, cross and triangle symbols.\r\n\r\n* The symbols are separate transparent models that can be reused in the future. \r\n* All symbols are running a `gazebo_ros_color` plugin, so it\u2019s possible to change its color via a ROS message.\r\n* The placard is a new model with a white background and the three symbols. Note that the symbols are transparent, so none of them are visible by default.\r\n* There's a `symbol_controller` plugin running in each placard to allow a fix configuration \\(e.g. green circle\\) or a random configuration. This plugin also accepts a service request to create a new random configuration.\r\n\r\n![](https://bitbucket.org/repo/BgXLzgM/images/2377027615-placard.gif)\r\n*Note: This pull request is built atop of pull request #27, which should be merged first.*", "title": "Symbols and placards", "destination": {"commit": {"hash": "f16ea892d96d", "type": "commit", "links": {"self": {"href": "data/repositories/osrf/vrx/commit/f16ea892d96d.json"}, "html": {"href": "#!/osrf/vrx/commits/f16ea892d96d"}}}, "repository": {"links": {"self": {"href": "data/repositories/osrf/vrx.json"}, "html": {"href": "#!/osrf/vrx"}, "avatar": {"href": "data/bytebucket.org/ravatar/{e278ca38-7edb-4e62-b785-46dff5617d98}ts=2274605"}}, "type": "repository", "name": "vrx", "full_name": "osrf/vrx", "uuid": "{e278ca38-7edb-4e62-b785-46dff5617d98}"}, "branch": {"name": "default"}}, "reason": "", "source": {"commit": {"hash": "7432c24d0962", "type": "commit", "links": {"self": {"href": "data/repositories/osrf/vrx/commit/7432c24d0962.json"}, "html": {"href": "#!/osrf/vrx/commits/7432c24d0962"}}}, "repository": {"links": {"self": {"href": "data/repositories/osrf/vrx.json"}, "html": {"href": "#!/osrf/vrx"}, "avatar": {"href": "data/bytebucket.org/ravatar/{e278ca38-7edb-4e62-b785-46dff5617d98}ts=2274605"}}, "type": "repository", "name": "vrx", "full_name": "osrf/vrx", "uuid": "{e278ca38-7edb-4e62-b785-46dff5617d98}"}, "branch": {"name": "placard"}}, "state": "OPEN", "author": {"display_name": "Carlos Ag\u00fcero", "uuid": "{da8a8e89-4bb0-421b-bd0e-dbbed3d4ed6a}", "links": {"self": {"href": "https://api.bitbucket.org/2.0/users/%7Bda8a8e89-4bb0-421b-bd0e-dbbed3d4ed6a%7D"}, "html": {"href": "https://bitbucket.org/%7Bda8a8e89-4bb0-421b-bd0e-dbbed3d4ed6a%7D/"}, "avatar": {"href": "data/secure.gravatar.com/avatar/692bf15758111acaddae4da15a47f9e5d=httpsavatar-management--avatars.us-west-2.prod.public.atl-paas.netinitialsCA-0.png"}}, "nickname": "caguero", "type": "user", "account_id": "557058:4ded1ddf-947e-4154-bbd1-3dba24f1bdbd"}, "date": "2018-07-26T01:27:24.659228+00:00"}, "pull_request": {"type": "pullrequest", "id": 31, "links": {"self": {"href": "data/repositories/osrf/vrx/pullrequests/31.json"}, "html": {"href": "#!/osrf/vrx/pull-requests/31"}}, "title": "Symbols and placards"}}, {"update": {"description": "Added the circle, cross and triangle symbols.\r\n\r\n* The symbols are separate transparent models that can be reused in the future. \r\n* All symbols are running a `gazebo_ros_color` plugin, so it\u2019s possible to change its color via a ROS message.\r\n* The placard is a new model with a white background and the three symbols. Note that the symbols are transparent, so none of them are visible by default.\r\n* There's a `symbol_controller` plugin running in each placard to allow a fix configuration \\(e.g. green circle\\) or a random configuration. This plugin also accepts a service request to create a new random configuration.\r\n\r\n![](https://bitbucket.org/repo/BgXLzgM/images/2377027615-placard.gif)\r\n*Note: This pull request is built atop of pull request #27, which should be merged first.*", "title": "Symbols and placards", "destination": {"commit": {"hash": "f16ea892d96d", "type": "commit", "links": {"self": {"href": "data/repositories/osrf/vrx/commit/f16ea892d96d.json"}, "html": {"href": "#!/osrf/vrx/commits/f16ea892d96d"}}}, "repository": {"links": {"self": {"href": "data/repositories/osrf/vrx.json"}, "html": {"href": "#!/osrf/vrx"}, "avatar": {"href": "data/bytebucket.org/ravatar/{e278ca38-7edb-4e62-b785-46dff5617d98}ts=2274605"}}, "type": "repository", "name": "vrx", "full_name": "osrf/vrx", "uuid": "{e278ca38-7edb-4e62-b785-46dff5617d98}"}, "branch": {"name": "default"}}, "reason": "", "source": {"commit": {"hash": "6a9566076b70", "type": "commit", "links": {"self": {"href": "data/repositories/osrf/vrx/commit/6a9566076b70.json"}, "html": {"href": "#!/osrf/vrx/commits/6a9566076b70"}}}, "repository": {"links": {"self": {"href": "data/repositories/osrf/vrx.json"}, "html": {"href": "#!/osrf/vrx"}, "avatar": {"href": "data/bytebucket.org/ravatar/{e278ca38-7edb-4e62-b785-46dff5617d98}ts=2274605"}}, "type": "repository", "name": "vrx", "full_name": "osrf/vrx", "uuid": "{e278ca38-7edb-4e62-b785-46dff5617d98}"}, "branch": {"name": "placard"}}, "state": "OPEN", "author": {"display_name": "Carlos Ag\u00fcero", "uuid": "{da8a8e89-4bb0-421b-bd0e-dbbed3d4ed6a}", "links": {"self": {"href": "https://api.bitbucket.org/2.0/users/%7Bda8a8e89-4bb0-421b-bd0e-dbbed3d4ed6a%7D"}, "html": {"href": "https://bitbucket.org/%7Bda8a8e89-4bb0-421b-bd0e-dbbed3d4ed6a%7D/"}, "avatar": {"href": "data/secure.gravatar.com/avatar/692bf15758111acaddae4da15a47f9e5d=httpsavatar-management--avatars.us-west-2.prod.public.atl-paas.netinitialsCA-0.png"}}, "nickname": "caguero", "type": "user", "account_id": "557058:4ded1ddf-947e-4154-bbd1-3dba24f1bdbd"}, "date": "2018-07-26T01:16:05.984018+00:00"}, "pull_request": {"type": "pullrequest", "id": 31, "links": {"self": {"href": "data/repositories/osrf/vrx/pullrequests/31.json"}, "html": {"href": "#!/osrf/vrx/pull-requests/31"}}, "title": "Symbols and placards"}}, {"comment": {"links": {"self": {"href": "data/repositories/osrf/vrx/pullrequests/31/comments/71070931.json"}, "html": {"href": "#!/osrf/vrx/pull-requests/31/_/diff#comment-71070931"}}, "deleted": false, "pullrequest": {"type": "pullrequest", "id": 31, "links": {"self": {"href": "data/repositories/osrf/vrx/pullrequests/31.json"}, "html": {"href": "#!/osrf/vrx/pull-requests/31"}}, "title": "Symbols and placards"}, "content": {"raw": "found in #30 that you should omit the scope for the model this is \\(just link instead of placard::link\\), allowing it to be included as a submodel", "markup": "markdown", "html": "<p>found in <a href=\"#!/osrf/vrx/issues/30/refine-default-sensor-configurations\" rel=\"nofollow\" title=\"Refine default sensor configurations\" class=\"ap-connect-link\"><s>#30</s></a> that you should omit the scope for the model this is (just link instead of placard::link), allowing it to be included as a submodel</p>", "type": "rendered"}, "created_on": "2018-07-26T00:48:01.266734+00:00", "user": {"display_name": "Kevin Allen", "uuid": "{29f672ad-72f4-434e-bb0e-c6f2f69974f2}", "links": {"self": {"href": "https://api.bitbucket.org/2.0/users/%7B29f672ad-72f4-434e-bb0e-c6f2f69974f2%7D"}, "html": {"href": "https://bitbucket.org/%7B29f672ad-72f4-434e-bb0e-c6f2f69974f2%7D/"}, "avatar": {"href": "data/secure.gravatar.com/avatar/355d0415f6040ffb168f44275ac2ee2fd=httpsavatar-management--avatars.us-west-2.prod.public.atl-paas.netinitialsKA-1.png"}}, "nickname": "kev-the-dev", "type": "user", "account_id": "5b04a6cf8a69f52b3ba2e5db"}, "inline": {}, "updated_on": "2018-07-26T00:48:01.284895+00:00", "type": "pullrequest_comment", "id": 71070931}, "pull_request": {"type": "pullrequest", "id": 31, "links": {"self": {"href": "data/repositories/osrf/vrx/pullrequests/31.json"}, "html": {"href": "#!/osrf/vrx/pull-requests/31"}}, "title": "Symbols and placards"}}, {"update": {"description": "Added the circle, cross and triangle symbols.\r\n\r\n* The symbols are separate transparent models that can be reused in the future. \r\n* All symbols are running a `gazebo_ros_color` plugin, so it\u2019s possible to change its color via a ROS message.\r\n* The placard is a new model with a white background and the three symbols. Note that the symbols are transparent, so none of them are visible by default.\r\n* There's a `symbol_controller` plugin running in each placard to allow a fix configuration \\(e.g. green circle\\) or a random configuration. This plugin also accepts a service request to create a new random configuration.\r\n\r\n![](https://bitbucket.org/repo/BgXLzgM/images/2377027615-placard.gif)\r\n*Note: This pull request is built atop of pull request #27, which should be merged first.*", "title": "Symbols and placards", "destination": {"commit": {"hash": "146bda203ed2", "type": "commit", "links": {"self": {"href": "data/repositories/osrf/vrx/commit/146bda203ed2.json"}, "html": {"href": "#!/osrf/vrx/commits/146bda203ed2"}}}, "repository": {"links": {"self": {"href": "data/repositories/osrf/vrx.json"}, "html": {"href": "#!/osrf/vrx"}, "avatar": {"href": "data/bytebucket.org/ravatar/{e278ca38-7edb-4e62-b785-46dff5617d98}ts=2274605"}}, "type": "repository", "name": "vrx", "full_name": "osrf/vrx", "uuid": "{e278ca38-7edb-4e62-b785-46dff5617d98}"}, "branch": {"name": "default"}}, "reason": "", "source": {"commit": {"hash": "3e451eb35755", "type": "commit", "links": {"self": {"href": "data/repositories/osrf/vrx/commit/3e451eb35755.json"}, "html": {"href": "#!/osrf/vrx/commits/3e451eb35755"}}}, "repository": {"links": {"self": {"href": "data/repositories/osrf/vrx.json"}, "html": {"href": "#!/osrf/vrx"}, "avatar": {"href": "data/bytebucket.org/ravatar/{e278ca38-7edb-4e62-b785-46dff5617d98}ts=2274605"}}, "type": "repository", "name": "vrx", "full_name": "osrf/vrx", "uuid": "{e278ca38-7edb-4e62-b785-46dff5617d98}"}, "branch": {"name": "placard"}}, "state": "OPEN", "author": {"display_name": "Carlos Ag\u00fcero", "uuid": "{da8a8e89-4bb0-421b-bd0e-dbbed3d4ed6a}", "links": {"self": {"href": "https://api.bitbucket.org/2.0/users/%7Bda8a8e89-4bb0-421b-bd0e-dbbed3d4ed6a%7D"}, "html": {"href": "https://bitbucket.org/%7Bda8a8e89-4bb0-421b-bd0e-dbbed3d4ed6a%7D/"}, "avatar": {"href": "data/secure.gravatar.com/avatar/692bf15758111acaddae4da15a47f9e5d=httpsavatar-management--avatars.us-west-2.prod.public.atl-paas.netinitialsCA-0.png"}}, "nickname": "caguero", "type": "user", "account_id": "557058:4ded1ddf-947e-4154-bbd1-3dba24f1bdbd"}, "date": "2018-07-25T22:42:41.452227+00:00"}, "pull_request": {"type": "pullrequest", "id": 31, "links": {"self": {"href": "data/repositories/osrf/vrx/pullrequests/31.json"}, "html": {"href": "#!/osrf/vrx/pull-requests/31"}}, "title": "Symbols and placards"}}, {"update": {"description": "Added the circle, cross and triangle symbols.\r\n\r\n* The symbols are separate transparent models that can be reused in the future. \r\n* All symbols are running a `gazebo_ros_color` plugin, so it\u2019s possible to change its color via a ROS message.\r\n* The placard is a new model with a white background and the three symbols. Note that the symbols are transparent, so none of them are visible by default.\r\n* There's a `symbol_controller` plugin running in each placard to allow a fix configuration \\(e.g. green circle\\) or a random configuration. This plugin also accepts a service request to create a new random configuration.\r\n\r\n![](https://bitbucket.org/repo/BgXLzgM/images/2377027615-placard.gif)\r\n*Note: This pull request is built atop of pull request #27, which should be merged first.*", "title": "Symbols and placards", "destination": {"commit": {"hash": "146bda203ed2", "type": "commit", "links": {"self": {"href": "data/repositories/osrf/vrx/commit/146bda203ed2.json"}, "html": {"href": "#!/osrf/vrx/commits/146bda203ed2"}}}, "repository": {"links": {"self": {"href": "data/repositories/osrf/vrx.json"}, "html": {"href": "#!/osrf/vrx"}, "avatar": {"href": "data/bytebucket.org/ravatar/{e278ca38-7edb-4e62-b785-46dff5617d98}ts=2274605"}}, "type": "repository", "name": "vrx", "full_name": "osrf/vrx", "uuid": "{e278ca38-7edb-4e62-b785-46dff5617d98}"}, "branch": {"name": "default"}}, "reason": "", "source": {"commit": {"hash": "8bbbe2664e39", "type": "commit", "links": {"self": {"href": "data/repositories/osrf/vrx/commit/8bbbe2664e39.json"}, "html": {"href": "#!/osrf/vrx/commits/8bbbe2664e39"}}}, "repository": {"links": {"self": {"href": "data/repositories/osrf/vrx.json"}, "html": {"href": "#!/osrf/vrx"}, "avatar": {"href": "data/bytebucket.org/ravatar/{e278ca38-7edb-4e62-b785-46dff5617d98}ts=2274605"}}, "type": "repository", "name": "vrx", "full_name": "osrf/vrx", "uuid": "{e278ca38-7edb-4e62-b785-46dff5617d98}"}, "branch": {"name": "placard"}}, "state": "OPEN", "author": {"display_name": "Carlos Ag\u00fcero", "uuid": "{da8a8e89-4bb0-421b-bd0e-dbbed3d4ed6a}", "links": {"self": {"href": "https://api.bitbucket.org/2.0/users/%7Bda8a8e89-4bb0-421b-bd0e-dbbed3d4ed6a%7D"}, "html": {"href": "https://bitbucket.org/%7Bda8a8e89-4bb0-421b-bd0e-dbbed3d4ed6a%7D/"}, "avatar": {"href": "data/secure.gravatar.com/avatar/692bf15758111acaddae4da15a47f9e5d=httpsavatar-management--avatars.us-west-2.prod.public.atl-paas.netinitialsCA-0.png"}}, "nickname": "caguero", "type": "user", "account_id": "557058:4ded1ddf-947e-4154-bbd1-3dba24f1bdbd"}, "date": "2018-07-25T22:41:42.546341+00:00"}, "pull_request": {"type": "pullrequest", "id": 31, "links": {"self": {"href": "data/repositories/osrf/vrx/pullrequests/31.json"}, "html": {"href": "#!/osrf/vrx/pull-requests/31"}}, "title": "Symbols and placards"}}, {"update": {"description": "Added the circle, cross and triangle symbols.\r\n\r\n* The symbols are separate transparent models that can be reused in the future. \r\n* All symbols are running a `gazebo_ros_color` plugin, so it\u2019s possible to change its color via a ROS message.\r\n* The placard is a new model with a white background and the three symbols. Note that the symbols are transparent, so none of them are visible by default.\r\n* There's a `symbol_controller` plugin running in each placard to allow a fix configuration \\(e.g. green circle\\) or a random configuration. This plugin also accepts a service request to create a new random configuration.\r\n\r\n![](https://bitbucket.org/repo/BgXLzgM/images/2377027615-placard.gif)\r\n*Note: This pull request is built atop of pull request #27, which should be merged first.*", "title": "Symbols and placards", "destination": {"commit": {"hash": "146bda203ed2", "type": "commit", "links": {"self": {"href": "data/repositories/osrf/vrx/commit/146bda203ed2.json"}, "html": {"href": "#!/osrf/vrx/commits/146bda203ed2"}}}, "repository": {"links": {"self": {"href": "data/repositories/osrf/vrx.json"}, "html": {"href": "#!/osrf/vrx"}, "avatar": {"href": "data/bytebucket.org/ravatar/{e278ca38-7edb-4e62-b785-46dff5617d98}ts=2274605"}}, "type": "repository", "name": "vrx", "full_name": "osrf/vrx", "uuid": "{e278ca38-7edb-4e62-b785-46dff5617d98}"}, "branch": {"name": "default"}}, "reason": "", "source": {"commit": {"hash": "8bbbe2664e39", "type": "commit", "links": {"self": {"href": "data/repositories/osrf/vrx/commit/8bbbe2664e39.json"}, "html": {"href": "#!/osrf/vrx/commits/8bbbe2664e39"}}}, "repository": {"links": {"self": {"href": "data/repositories/osrf/vrx.json"}, "html": {"href": "#!/osrf/vrx"}, "avatar": {"href": "data/bytebucket.org/ravatar/{e278ca38-7edb-4e62-b785-46dff5617d98}ts=2274605"}}, "type": "repository", "name": "vrx", "full_name": "osrf/vrx", "uuid": "{e278ca38-7edb-4e62-b785-46dff5617d98}"}, "branch": {"name": "placard"}}, "state": "OPEN", "author": {"display_name": "Carlos Ag\u00fcero", "uuid": "{da8a8e89-4bb0-421b-bd0e-dbbed3d4ed6a}", "links": {"self": {"href": "https://api.bitbucket.org/2.0/users/%7Bda8a8e89-4bb0-421b-bd0e-dbbed3d4ed6a%7D"}, "html": {"href": "https://bitbucket.org/%7Bda8a8e89-4bb0-421b-bd0e-dbbed3d4ed6a%7D/"}, "avatar": {"href": "data/secure.gravatar.com/avatar/692bf15758111acaddae4da15a47f9e5d=httpsavatar-management--avatars.us-west-2.prod.public.atl-paas.netinitialsCA-0.png"}}, "nickname": "caguero", "type": "user", "account_id": "557058:4ded1ddf-947e-4154-bbd1-3dba24f1bdbd"}, "date": "2018-07-25T22:41:42.512771+00:00"}, "pull_request": {"type": "pullrequest", "id": 31, "links": {"self": {"href": "data/repositories/osrf/vrx/pullrequests/31.json"}, "html": {"href": "#!/osrf/vrx/pull-requests/31"}}, "title": "Symbols and placards"}}]}