{"pagelen": 100, "values": [{"links": {"self": {"href": "data/repositories/osrf/vrx/issues/151/comments/53559171.json"}, "html": {"href": "#!/osrf/vrx/issues/151#comment-53559171"}}, "issue": {"links": {"self": {"href": "data/repositories/osrf/vrx/issues/151.json"}}, "type": "issue", "id": 151, "repository": {"links": {"self": {"href": "data/repositories/osrf/vrx.json"}, "html": {"href": "#!/osrf/vrx"}, "avatar": {"href": "data/bytebucket.org/ravatar/{e278ca38-7edb-4e62-b785-46dff5617d98}ts=2274605"}}, "type": "repository", "name": "vrx", "full_name": "osrf/vrx", "uuid": "{e278ca38-7edb-4e62-b785-46dff5617d98}"}, "title": "Investigate oyaml dependency"}, "content": {"raw": null, "markup": "markdown", "html": "", "type": "rendered"}, "created_on": "2019-08-22T21:35:51.074422+00:00", "user": {"display_name": "Tyler Lum", "uuid": "{305d9368-23ba-4f72-b1d4-7d17d2a062d8}", "links": {"self": {"href": "https://api.bitbucket.org/2.0/users/%7B305d9368-23ba-4f72-b1d4-7d17d2a062d8%7D"}, "html": {"href": "https://bitbucket.org/%7B305d9368-23ba-4f72-b1d4-7d17d2a062d8%7D/"}, "avatar": {"href": "https://avatar-management--avatars.us-west-2.prod.public.atl-paas.net/5b96b66385af94340e7cabce/b8bb780f-62b7-47f8-9d03-ee65c7d17ad4/128"}}, "nickname": "tylerlum", "type": "user", "account_id": "5b96b66385af94340e7cabce"}, "updated_on": null, "type": "issue_comment", "id": 53559171}, {"links": {"self": {"href": "data/repositories/osrf/vrx/issues/151/comments/53559180.json"}, "html": {"href": "#!/osrf/vrx/issues/151#comment-53559180"}}, "issue": {"links": {"self": {"href": "data/repositories/osrf/vrx/issues/151.json"}}, "type": "issue", "id": 151, "repository": {"links": {"self": {"href": "data/repositories/osrf/vrx.json"}, "html": {"href": "#!/osrf/vrx"}, "avatar": {"href": "data/bytebucket.org/ravatar/{e278ca38-7edb-4e62-b785-46dff5617d98}ts=2274605"}}, "type": "repository", "name": "vrx", "full_name": "osrf/vrx", "uuid": "{e278ca38-7edb-4e62-b785-46dff5617d98}"}, "title": "Investigate oyaml dependency"}, "content": {"raw": "The reason for the switch to oyaml was because there were many warnings about safety that came up using yaml. This should not be an issue, but should be noted.", "markup": "markdown", "html": "<p>The reason for the switch to oyaml was because there were many warnings about safety that came up using yaml. This should not be an issue, but should be noted.</p>", "type": "rendered"}, "created_on": "2019-08-22T21:36:46.107757+00:00", "user": {"display_name": "Tyler Lum", "uuid": "{305d9368-23ba-4f72-b1d4-7d17d2a062d8}", "links": {"self": {"href": "https://api.bitbucket.org/2.0/users/%7B305d9368-23ba-4f72-b1d4-7d17d2a062d8%7D"}, "html": {"href": "https://bitbucket.org/%7B305d9368-23ba-4f72-b1d4-7d17d2a062d8%7D/"}, "avatar": {"href": "https://avatar-management--avatars.us-west-2.prod.public.atl-paas.net/5b96b66385af94340e7cabce/b8bb780f-62b7-47f8-9d03-ee65c7d17ad4/128"}}, "nickname": "tylerlum", "type": "user", "account_id": "5b96b66385af94340e7cabce"}, "updated_on": null, "type": "issue_comment", "id": 53559180}], "page": 1, "size": 2}