{"links": {"self": {"href": "data/repositories/osrf/vrx/pullrequests/122/comments/107363497.json"}, "code": {"href": "https://api.bitbucket.org/2.0/repositories/osrf/vrx/diff/osrf/vrx:281853f0e0b7..9ff5de59c1e7?path=usv_gazebo_plugins%2Fsrc%2Fbuoyancy_gazebo_plugin.cc"}, "html": {"href": "#!/osrf/vrx/pull-requests/122/_/diff#comment-107363497"}}, "parent": {"id": 107362934, "links": {"self": {"href": "data/repositories/osrf/vrx/pullrequests/122/comments/107362934.json"}, "html": {"href": "#!/osrf/vrx/pull-requests/122/_/diff#comment-107362934"}}}, "deleted": false, "pullrequest": {"type": "pullrequest", "id": 122, "links": {"self": {"href": "data/repositories/osrf/vrx/pullrequests/122.json"}, "html": {"href": "#!/osrf/vrx/pull-requests/122"}}, "title": "Issue#94 buoyancy"}, "content": {"raw": "The reference is brief, but I think it is just a convention for the units.  They specify the coefficient in units of \\[1/s\\] so you need L^2 to get the expression to be in units of torque \\[Nm\\].  I think we are find justifying it with the reference.  ", "markup": "markdown", "html": "<p>The reference is brief, but I think it is just a convention for the units.  They specify the coefficient in units of [1/s] so you need L^2 to get the expression to be in units of torque [Nm].  I think we are find justifying it with the reference.  </p>", "type": "rendered"}, "created_on": "2019-06-27T17:55:10.200747+00:00", "user": {"display_name": "Brian Bingham", "uuid": "{9cdea257-248f-486e-8858-49d8485a916f}", "links": {"self": {"href": "https://api.bitbucket.org/2.0/users/%7B9cdea257-248f-486e-8858-49d8485a916f%7D"}, "html": {"href": "https://bitbucket.org/%7B9cdea257-248f-486e-8858-49d8485a916f%7D/"}, "avatar": {"href": "https://avatar-management--avatars.us-west-2.prod.public.atl-paas.net/557058:6c52d6e5-77e0-41a8-8b6e-cb9462f4d5f1/7a690884-fc47-4bca-9c2b-baecee4d3dc9/128"}}, "nickname": "brian_bingham", "type": "user", "account_id": "557058:6c52d6e5-77e0-41a8-8b6e-cb9462f4d5f1"}, "inline": {"to": 291, "from": null, "outdated": true, "path": "usv_gazebo_plugins/src/buoyancy_gazebo_plugin.cc"}, "updated_on": "2019-06-27T17:55:10.219809+00:00", "type": "pullrequest_comment", "id": 107363497}