{"pagelen": 50, "values": [{"update": {"description": "* functional?\r\n* includes the yaml files in repository\r\n* fixed xacro insert block ordering issue\r\n* fixed ambient light and fog", "title": "Ocean wave xacro", "destination": {"commit": {"hash": "c5e480cdb396", "type": "commit", "links": {"self": {"href": "data/repositories/osrf/vrx/commit/c5e480cdb396.json"}, "html": {"href": "#!/osrf/vrx/commits/c5e480cdb396"}}}, "repository": {"links": {"self": {"href": "data/repositories/osrf/vrx.json"}, "html": {"href": "#!/osrf/vrx"}, "avatar": {"href": "data/bytebucket.org/ravatar/{e278ca38-7edb-4e62-b785-46dff5617d98}ts=2274605"}}, "type": "repository", "name": "vrx", "full_name": "osrf/vrx", "uuid": "{e278ca38-7edb-4e62-b785-46dff5617d98}"}, "branch": {"name": "default"}}, "reason": "", "source": {"commit": {"hash": "d1e04e549968", "type": "commit", "links": {"self": {"href": "data/repositories/osrf/vrx/commit/d1e04e549968.json"}, "html": {"href": "#!/osrf/vrx/commits/d1e04e549968"}}}, "repository": {"links": {"self": {"href": "data/repositories/osrf/vrx.json"}, "html": {"href": "#!/osrf/vrx"}, "avatar": {"href": "data/bytebucket.org/ravatar/{e278ca38-7edb-4e62-b785-46dff5617d98}ts=2274605"}}, "type": "repository", "name": "vrx", "full_name": "osrf/vrx", "uuid": "{e278ca38-7edb-4e62-b785-46dff5617d98}"}, "branch": {"name": "ocean-wave-xacro"}}, "state": "MERGED", "author": {"display_name": "Marshall Rawson", "uuid": "{e6f8e5b5-5261-44d3-b2d4-092469c4157a}", "links": {"self": {"href": "https://api.bitbucket.org/2.0/users/%7Be6f8e5b5-5261-44d3-b2d4-092469c4157a%7D"}, "html": {"href": "https://bitbucket.org/%7Be6f8e5b5-5261-44d3-b2d4-092469c4157a%7D/"}, "avatar": {"href": "data/secure.gravatar.com/avatar/bd54845fa0ad1be5a529eb87d738f221d=httpsavatar-management--avatars.us-west-2.prod.public.atl-paas.netinitialsMR-4.png"}}, "nickname": "MarshallRawson", "type": "user", "account_id": "5ce2e28709c5fa0fd9fb0c6c"}, "date": "2019-07-25T16:24:39.733268+00:00"}, "pull_request": {"type": "pullrequest", "id": 150, "links": {"self": {"href": "data/repositories/osrf/vrx/pullrequests/150.json"}, "html": {"href": "#!/osrf/vrx/pull-requests/150"}}, "title": "Ocean wave xacro"}}, {"approval": {"date": "2019-07-25T16:24:06.874684+00:00", "pullrequest": {"type": "pullrequest", "id": 150, "links": {"self": {"href": "data/repositories/osrf/vrx/pullrequests/150.json"}, "html": {"href": "#!/osrf/vrx/pull-requests/150"}}, "title": "Ocean wave xacro"}, "user": {"display_name": "Marshall Rawson", "uuid": "{e6f8e5b5-5261-44d3-b2d4-092469c4157a}", "links": {"self": {"href": "https://api.bitbucket.org/2.0/users/%7Be6f8e5b5-5261-44d3-b2d4-092469c4157a%7D"}, "html": {"href": "https://bitbucket.org/%7Be6f8e5b5-5261-44d3-b2d4-092469c4157a%7D/"}, "avatar": {"href": "data/secure.gravatar.com/avatar/bd54845fa0ad1be5a529eb87d738f221d=httpsavatar-management--avatars.us-west-2.prod.public.atl-paas.netinitialsMR-4.png"}}, "nickname": "MarshallRawson", "type": "user", "account_id": "5ce2e28709c5fa0fd9fb0c6c"}}, "pull_request": {"type": "pullrequest", "id": 150, "links": {"self": {"href": "data/repositories/osrf/vrx/pullrequests/150.json"}, "html": {"href": "#!/osrf/vrx/pull-requests/150"}}, "title": "Ocean wave xacro"}}, {"update": {"description": "* functional?\r\n* includes the yaml files in repository\r\n* fixed xacro insert block ordering issue\r\n* fixed ambient light and fog", "title": "Ocean wave xacro", "destination": {"commit": {"hash": "c5e480cdb396", "type": "commit", "links": {"self": {"href": "data/repositories/osrf/vrx/commit/c5e480cdb396.json"}, "html": {"href": "#!/osrf/vrx/commits/c5e480cdb396"}}}, "repository": {"links": {"self": {"href": "data/repositories/osrf/vrx.json"}, "html": {"href": "#!/osrf/vrx"}, "avatar": {"href": "data/bytebucket.org/ravatar/{e278ca38-7edb-4e62-b785-46dff5617d98}ts=2274605"}}, "type": "repository", "name": "vrx", "full_name": "osrf/vrx", "uuid": "{e278ca38-7edb-4e62-b785-46dff5617d98}"}, "branch": {"name": "default"}}, "reason": "", "source": {"commit": {"hash": "d1e04e549968", "type": "commit", "links": {"self": {"href": "data/repositories/osrf/vrx/commit/d1e04e549968.json"}, "html": {"href": "#!/osrf/vrx/commits/d1e04e549968"}}}, "repository": {"links": {"self": {"href": "data/repositories/osrf/vrx.json"}, "html": {"href": "#!/osrf/vrx"}, "avatar": {"href": "data/bytebucket.org/ravatar/{e278ca38-7edb-4e62-b785-46dff5617d98}ts=2274605"}}, "type": "repository", "name": "vrx", "full_name": "osrf/vrx", "uuid": "{e278ca38-7edb-4e62-b785-46dff5617d98}"}, "branch": {"name": "ocean-wave-xacro"}}, "state": "OPEN", "author": {"display_name": "Tyler Lum", "uuid": "{305d9368-23ba-4f72-b1d4-7d17d2a062d8}", "links": {"self": {"href": "https://api.bitbucket.org/2.0/users/%7B305d9368-23ba-4f72-b1d4-7d17d2a062d8%7D"}, "html": {"href": "https://bitbucket.org/%7B305d9368-23ba-4f72-b1d4-7d17d2a062d8%7D/"}, "avatar": {"href": "https://avatar-management--avatars.us-west-2.prod.public.atl-paas.net/5b96b66385af94340e7cabce/b8bb780f-62b7-47f8-9d03-ee65c7d17ad4/128"}}, "nickname": "tylerlum", "type": "user", "account_id": "5b96b66385af94340e7cabce"}, "date": "2019-07-25T16:04:42.764094+00:00"}, "pull_request": {"type": "pullrequest", "id": 150, "links": {"self": {"href": "data/repositories/osrf/vrx/pullrequests/150.json"}, "html": {"href": "#!/osrf/vrx/pull-requests/150"}}, "title": "Ocean wave xacro"}}, {"comment": {"links": {"self": {"href": "data/repositories/osrf/vrx/pullrequests/150/comments/110594958.json"}, "html": {"href": "#!/osrf/vrx/pull-requests/150/_/diff#comment-110594958"}}, "deleted": false, "pullrequest": {"type": "pullrequest", "id": 150, "links": {"self": {"href": "data/repositories/osrf/vrx/pullrequests/150.json"}, "html": {"href": "#!/osrf/vrx/pull-requests/150"}}, "title": "Ocean wave xacro"}, "content": {"raw": "@{5ce2e28709c5fa0fd9fb0c6c} All things look good on my end. Let me know when you remove that old unneeded model and then merge if you feel it is good \\(I am \u201cauthor\u201d can\u2019t approve\\)", "markup": "markdown", "html": "<p><span class=\"ap-mention\" data-atlassian-id=\"5ce2e28709c5fa0fd9fb0c6c\">@Marshall Rawson</span> All things look good on my end. Let me know when you remove that old unneeded model and then merge if you feel it is good (I am \u201cauthor\u201d can\u2019t approve)</p>", "type": "rendered"}, "created_on": "2019-07-25T00:27:52.688716+00:00", "user": {"display_name": "Tyler Lum", "uuid": "{305d9368-23ba-4f72-b1d4-7d17d2a062d8}", "links": {"self": {"href": "https://api.bitbucket.org/2.0/users/%7B305d9368-23ba-4f72-b1d4-7d17d2a062d8%7D"}, "html": {"href": "https://bitbucket.org/%7B305d9368-23ba-4f72-b1d4-7d17d2a062d8%7D/"}, "avatar": {"href": "https://avatar-management--avatars.us-west-2.prod.public.atl-paas.net/5b96b66385af94340e7cabce/b8bb780f-62b7-47f8-9d03-ee65c7d17ad4/128"}}, "nickname": "tylerlum", "type": "user", "account_id": "5b96b66385af94340e7cabce"}, "updated_on": "2019-07-25T00:27:52.703136+00:00", "type": "pullrequest_comment", "id": 110594958}, "pull_request": {"type": "pullrequest", "id": 150, "links": {"self": {"href": "data/repositories/osrf/vrx/pullrequests/150.json"}, "html": {"href": "#!/osrf/vrx/pull-requests/150"}}, "title": "Ocean wave xacro"}}, {"comment": {"links": {"self": {"href": "data/repositories/osrf/vrx/pullrequests/150/comments/110594836.json"}, "html": {"href": "#!/osrf/vrx/pull-requests/150/_/diff#comment-110594836"}}, "parent": {"id": 110594663, "links": {"self": {"href": "data/repositories/osrf/vrx/pullrequests/150/comments/110594663.json"}, "html": {"href": "#!/osrf/vrx/pull-requests/150/_/diff#comment-110594663"}}}, "deleted": false, "pullrequest": {"type": "pullrequest", "id": 150, "links": {"self": {"href": "data/repositories/osrf/vrx/pullrequests/150.json"}, "html": {"href": "#!/osrf/vrx/pull-requests/150"}}, "title": "Ocean wave xacro"}, "content": {"raw": "Otherwise the task files would be hard to distinguish, eg:\n\n```\n\u279c  [Wed Jul 24 17:24:42 PDT 2019] vrx ls ~/worlds\nshallow_test0.world   shallow_test11.world  shallow_test2.world  shallow_test4.world  shallow_test6.world  shallow_test8.world\nshallow_test10.world  shallow_test1.world   shallow_test3.world  shallow_test5.world  shallow_test7.world  shallow_test9.world\n```", "markup": "markdown", "html": "<p>Otherwise the task files would be hard to distinguish, eg:</p>\n<div class=\"codehilite\"><pre><span></span>\u279c  [Wed Jul 24 17:24:42 PDT 2019] vrx ls ~/worlds\nshallow_test0.world   shallow_test11.world  shallow_test2.world  shallow_test4.world  shallow_test6.world  shallow_test8.world\nshallow_test10.world  shallow_test1.world   shallow_test3.world  shallow_test5.world  shallow_test7.world  shallow_test9.world\n</pre></div>", "type": "rendered"}, "created_on": "2019-07-25T00:25:32.845141+00:00", "user": {"display_name": "Tyler Lum", "uuid": "{305d9368-23ba-4f72-b1d4-7d17d2a062d8}", "links": {"self": {"href": "https://api.bitbucket.org/2.0/users/%7B305d9368-23ba-4f72-b1d4-7d17d2a062d8%7D"}, "html": {"href": "https://bitbucket.org/%7B305d9368-23ba-4f72-b1d4-7d17d2a062d8%7D/"}, "avatar": {"href": "https://avatar-management--avatars.us-west-2.prod.public.atl-paas.net/5b96b66385af94340e7cabce/b8bb780f-62b7-47f8-9d03-ee65c7d17ad4/128"}}, "nickname": "tylerlum", "type": "user", "account_id": "5b96b66385af94340e7cabce"}, "updated_on": "2019-07-25T00:25:32.855776+00:00", "type": "pullrequest_comment", "id": 110594836}, "pull_request": {"type": "pullrequest", "id": 150, "links": {"self": {"href": "data/repositories/osrf/vrx/pullrequests/150.json"}, "html": {"href": "#!/osrf/vrx/pull-requests/150"}}, "title": "Ocean wave xacro"}}, {"comment": {"links": {"self": {"href": "data/repositories/osrf/vrx/pullrequests/150/comments/110594663.json"}, "html": {"href": "#!/osrf/vrx/pull-requests/150/_/diff#comment-110594663"}}, "deleted": false, "pullrequest": {"type": "pullrequest", "id": 150, "links": {"self": {"href": "data/repositories/osrf/vrx/pullrequests/150.json"}, "html": {"href": "#!/osrf/vrx/pull-requests/150"}}, "title": "Ocean wave xacro"}, "content": {"raw": "I broke up the shallow and deep yamls into 6 different yamls each. This is probably what we want to do, for clarity and ease of understanding.", "markup": "markdown", "html": "<p>I broke up the shallow and deep yamls into 6 different yamls each. This is probably what we want to do, for clarity and ease of understanding.</p>", "type": "rendered"}, "created_on": "2019-07-25T00:22:19.580777+00:00", "user": {"display_name": "Tyler Lum", "uuid": "{305d9368-23ba-4f72-b1d4-7d17d2a062d8}", "links": {"self": {"href": "https://api.bitbucket.org/2.0/users/%7B305d9368-23ba-4f72-b1d4-7d17d2a062d8%7D"}, "html": {"href": "https://bitbucket.org/%7B305d9368-23ba-4f72-b1d4-7d17d2a062d8%7D/"}, "avatar": {"href": "https://avatar-management--avatars.us-west-2.prod.public.atl-paas.net/5b96b66385af94340e7cabce/b8bb780f-62b7-47f8-9d03-ee65c7d17ad4/128"}}, "nickname": "tylerlum", "type": "user", "account_id": "5b96b66385af94340e7cabce"}, "updated_on": "2019-07-25T00:22:19.586290+00:00", "type": "pullrequest_comment", "id": 110594663}, "pull_request": {"type": "pullrequest", "id": 150, "links": {"self": {"href": "data/repositories/osrf/vrx/pullrequests/150.json"}, "html": {"href": "#!/osrf/vrx/pull-requests/150"}}, "title": "Ocean wave xacro"}}, {"update": {"description": "* functional?\r\n* includes the yaml files in repository\r\n* fixed xacro insert block ordering issue\r\n* fixed ambient light and fog", "title": "Ocean wave xacro", "destination": {"commit": {"hash": "0af146668f69", "type": "commit", "links": {"self": {"href": "data/repositories/osrf/vrx/commit/0af146668f69.json"}, "html": {"href": "#!/osrf/vrx/commits/0af146668f69"}}}, "repository": {"links": {"self": {"href": "data/repositories/osrf/vrx.json"}, "html": {"href": "#!/osrf/vrx"}, "avatar": {"href": "data/bytebucket.org/ravatar/{e278ca38-7edb-4e62-b785-46dff5617d98}ts=2274605"}}, "type": "repository", "name": "vrx", "full_name": "osrf/vrx", "uuid": "{e278ca38-7edb-4e62-b785-46dff5617d98}"}, "branch": {"name": "default"}}, "reason": "", "source": {"commit": {"hash": "b8883b793e3a", "type": "commit", "links": {"self": {"href": "data/repositories/osrf/vrx/commit/b8883b793e3a.json"}, "html": {"href": "#!/osrf/vrx/commits/b8883b793e3a"}}}, "repository": {"links": {"self": {"href": "data/repositories/osrf/vrx.json"}, "html": {"href": "#!/osrf/vrx"}, "avatar": {"href": "data/bytebucket.org/ravatar/{e278ca38-7edb-4e62-b785-46dff5617d98}ts=2274605"}}, "type": "repository", "name": "vrx", "full_name": "osrf/vrx", "uuid": "{e278ca38-7edb-4e62-b785-46dff5617d98}"}, "branch": {"name": "ocean-wave-xacro"}}, "state": "OPEN", "author": {"display_name": "Tyler Lum", "uuid": "{305d9368-23ba-4f72-b1d4-7d17d2a062d8}", "links": {"self": {"href": "https://api.bitbucket.org/2.0/users/%7B305d9368-23ba-4f72-b1d4-7d17d2a062d8%7D"}, "html": {"href": "https://bitbucket.org/%7B305d9368-23ba-4f72-b1d4-7d17d2a062d8%7D/"}, "avatar": {"href": "https://avatar-management--avatars.us-west-2.prod.public.atl-paas.net/5b96b66385af94340e7cabce/b8bb780f-62b7-47f8-9d03-ee65c7d17ad4/128"}}, "nickname": "tylerlum", "type": "user", "account_id": "5b96b66385af94340e7cabce"}, "date": "2019-07-25T00:07:40.161351+00:00"}, "pull_request": {"type": "pullrequest", "id": 150, "links": {"self": {"href": "data/repositories/osrf/vrx/pullrequests/150.json"}, "html": {"href": "#!/osrf/vrx/pull-requests/150"}}, "title": "Ocean wave xacro"}}, {"update": {"description": "* functional?\r\n* includes the yaml files in repository\r\n* fixed xacro insert block ordering issue\r\n* fixed ambient light and fog", "title": "Ocean wave xacro", "destination": {"commit": {"hash": "0af146668f69", "type": "commit", "links": {"self": {"href": "data/repositories/osrf/vrx/commit/0af146668f69.json"}, "html": {"href": "#!/osrf/vrx/commits/0af146668f69"}}}, "repository": {"links": {"self": {"href": "data/repositories/osrf/vrx.json"}, "html": {"href": "#!/osrf/vrx"}, "avatar": {"href": "data/bytebucket.org/ravatar/{e278ca38-7edb-4e62-b785-46dff5617d98}ts=2274605"}}, "type": "repository", "name": "vrx", "full_name": "osrf/vrx", "uuid": "{e278ca38-7edb-4e62-b785-46dff5617d98}"}, "branch": {"name": "default"}}, "reason": "", "source": {"commit": {"hash": "398b56186062", "type": "commit", "links": {"self": {"href": "data/repositories/osrf/vrx/commit/398b56186062.json"}, "html": {"href": "#!/osrf/vrx/commits/398b56186062"}}}, "repository": {"links": {"self": {"href": "data/repositories/osrf/vrx.json"}, "html": {"href": "#!/osrf/vrx"}, "avatar": {"href": "data/bytebucket.org/ravatar/{e278ca38-7edb-4e62-b785-46dff5617d98}ts=2274605"}}, "type": "repository", "name": "vrx", "full_name": "osrf/vrx", "uuid": "{e278ca38-7edb-4e62-b785-46dff5617d98}"}, "branch": {"name": "ocean-wave-xacro"}}, "state": "OPEN", "author": {"display_name": "Marshall Rawson", "uuid": "{e6f8e5b5-5261-44d3-b2d4-092469c4157a}", "links": {"self": {"href": "https://api.bitbucket.org/2.0/users/%7Be6f8e5b5-5261-44d3-b2d4-092469c4157a%7D"}, "html": {"href": "https://bitbucket.org/%7Be6f8e5b5-5261-44d3-b2d4-092469c4157a%7D/"}, "avatar": {"href": "data/secure.gravatar.com/avatar/bd54845fa0ad1be5a529eb87d738f221d=httpsavatar-management--avatars.us-west-2.prod.public.atl-paas.netinitialsMR-4.png"}}, "nickname": "MarshallRawson", "type": "user", "account_id": "5ce2e28709c5fa0fd9fb0c6c"}, "date": "2019-07-24T23:57:16.601227+00:00"}, "pull_request": {"type": "pullrequest", "id": 150, "links": {"self": {"href": "data/repositories/osrf/vrx/pullrequests/150.json"}, "html": {"href": "#!/osrf/vrx/pull-requests/150"}}, "title": "Ocean wave xacro"}}, {"update": {"description": "* functional?\r\n* includes the yaml files in repository\r\n* fixed xacro insert block ordering issue\r\n* fixed ambient light and fog", "title": "Ocean wave xacro", "destination": {"commit": {"hash": "0af146668f69", "type": "commit", "links": {"self": {"href": "data/repositories/osrf/vrx/commit/0af146668f69.json"}, "html": {"href": "#!/osrf/vrx/commits/0af146668f69"}}}, "repository": {"links": {"self": {"href": "data/repositories/osrf/vrx.json"}, "html": {"href": "#!/osrf/vrx"}, "avatar": {"href": "data/bytebucket.org/ravatar/{e278ca38-7edb-4e62-b785-46dff5617d98}ts=2274605"}}, "type": "repository", "name": "vrx", "full_name": "osrf/vrx", "uuid": "{e278ca38-7edb-4e62-b785-46dff5617d98}"}, "branch": {"name": "default"}}, "reason": "", "source": {"commit": {"hash": "ce3fad6d7eae", "type": "commit", "links": {"self": {"href": "data/repositories/osrf/vrx/commit/ce3fad6d7eae.json"}, "html": {"href": "#!/osrf/vrx/commits/ce3fad6d7eae"}}}, "repository": {"links": {"self": {"href": "data/repositories/osrf/vrx.json"}, "html": {"href": "#!/osrf/vrx"}, "avatar": {"href": "data/bytebucket.org/ravatar/{e278ca38-7edb-4e62-b785-46dff5617d98}ts=2274605"}}, "type": "repository", "name": "vrx", "full_name": "osrf/vrx", "uuid": "{e278ca38-7edb-4e62-b785-46dff5617d98}"}, "branch": {"name": "ocean-wave-xacro"}}, "state": "OPEN", "author": {"display_name": "Tyler Lum", "uuid": "{305d9368-23ba-4f72-b1d4-7d17d2a062d8}", "links": {"self": {"href": "https://api.bitbucket.org/2.0/users/%7B305d9368-23ba-4f72-b1d4-7d17d2a062d8%7D"}, "html": {"href": "https://bitbucket.org/%7B305d9368-23ba-4f72-b1d4-7d17d2a062d8%7D/"}, "avatar": {"href": "https://avatar-management--avatars.us-west-2.prod.public.atl-paas.net/5b96b66385af94340e7cabce/b8bb780f-62b7-47f8-9d03-ee65c7d17ad4/128"}}, "nickname": "tylerlum", "type": "user", "account_id": "5b96b66385af94340e7cabce"}, "date": "2019-07-24T23:34:08.208222+00:00"}, "pull_request": {"type": "pullrequest", "id": 150, "links": {"self": {"href": "data/repositories/osrf/vrx/pullrequests/150.json"}, "html": {"href": "#!/osrf/vrx/pull-requests/150"}}, "title": "Ocean wave xacro"}}, {"update": {"description": "* functional?\r\n* includes the yaml files in repository\r\n* fixed xacro insert block ordering issue\r\n* fixed ambient light and fog", "title": "Ocean wave xacro", "destination": {"commit": {"hash": "0af146668f69", "type": "commit", "links": {"self": {"href": "data/repositories/osrf/vrx/commit/0af146668f69.json"}, "html": {"href": "#!/osrf/vrx/commits/0af146668f69"}}}, "repository": {"links": {"self": {"href": "data/repositories/osrf/vrx.json"}, "html": {"href": "#!/osrf/vrx"}, "avatar": {"href": "data/bytebucket.org/ravatar/{e278ca38-7edb-4e62-b785-46dff5617d98}ts=2274605"}}, "type": "repository", "name": "vrx", "full_name": "osrf/vrx", "uuid": "{e278ca38-7edb-4e62-b785-46dff5617d98}"}, "branch": {"name": "default"}}, "reason": "", "source": {"commit": {"hash": "ce3fad6d7eae", "type": "commit", "links": {"self": {"href": "data/repositories/osrf/vrx/commit/ce3fad6d7eae.json"}, "html": {"href": "#!/osrf/vrx/commits/ce3fad6d7eae"}}}, "repository": {"links": {"self": {"href": "data/repositories/osrf/vrx.json"}, "html": {"href": "#!/osrf/vrx"}, "avatar": {"href": "data/bytebucket.org/ravatar/{e278ca38-7edb-4e62-b785-46dff5617d98}ts=2274605"}}, "type": "repository", "name": "vrx", "full_name": "osrf/vrx", "uuid": "{e278ca38-7edb-4e62-b785-46dff5617d98}"}, "branch": {"name": "ocean-wave-xacro"}}, "state": "OPEN", "author": {"display_name": "Tyler Lum", "uuid": "{305d9368-23ba-4f72-b1d4-7d17d2a062d8}", "links": {"self": {"href": "https://api.bitbucket.org/2.0/users/%7B305d9368-23ba-4f72-b1d4-7d17d2a062d8%7D"}, "html": {"href": "https://bitbucket.org/%7B305d9368-23ba-4f72-b1d4-7d17d2a062d8%7D/"}, "avatar": {"href": "https://avatar-management--avatars.us-west-2.prod.public.atl-paas.net/5b96b66385af94340e7cabce/b8bb780f-62b7-47f8-9d03-ee65c7d17ad4/128"}}, "nickname": "tylerlum", "type": "user", "account_id": "5b96b66385af94340e7cabce"}, "date": "2019-07-24T23:34:08.165420+00:00"}, "pull_request": {"type": "pullrequest", "id": 150, "links": {"self": {"href": "data/repositories/osrf/vrx/pullrequests/150.json"}, "html": {"href": "#!/osrf/vrx/pull-requests/150"}}, "title": "Ocean wave xacro"}}]}