{"links": {"self": {"href": "data/repositories/osrf/vrx/pullrequests/159/comments/113309321.json"}, "code": {"href": "https://api.bitbucket.org/2.0/repositories/osrf/vrx/diff/osrf/vrx:c4586672595f..b4757bbf9d60?path=vrx_gazebo%2Fsrc%2Fperception_scoring_plugin.cc"}, "html": {"href": "#!/osrf/vrx/pull-requests/159/_/diff#comment-113309321"}}, "deleted": false, "pullrequest": {"type": "pullrequest", "id": 159, "links": {"self": {"href": "data/repositories/osrf/vrx/pullrequests/159.json"}, "html": {"href": "#!/osrf/vrx/pull-requests/159"}}, "title": "Issue#127 perception task plugin"}, "content": {"raw": "I tweaked this block to avoid the `else` part by initializing the variable to `5` here. [c458667](#!/osrf/vrx/commits/c4586672595f52f7c8842ae9bf77e3468bd184cf?at=default)", "markup": "markdown", "html": "<p>I tweaked this block to avoid the <code>else</code> part by initializing the variable to <code>5</code> here. <a data-is-external-link=\"true\" href=\"#!/osrf/vrx/commits/c4586672595f52f7c8842ae9bf77e3468bd184cf?at=default\" rel=\"nofollow\">c458667</a></p>", "type": "rendered"}, "created_on": "2019-08-15T20:58:00.092100+00:00", "user": {"display_name": "Carlos Ag\u00fcero", "uuid": "{da8a8e89-4bb0-421b-bd0e-dbbed3d4ed6a}", "links": {"self": {"href": "https://api.bitbucket.org/2.0/users/%7Bda8a8e89-4bb0-421b-bd0e-dbbed3d4ed6a%7D"}, "html": {"href": "https://bitbucket.org/%7Bda8a8e89-4bb0-421b-bd0e-dbbed3d4ed6a%7D/"}, "avatar": {"href": "data/secure.gravatar.com/avatar/692bf15758111acaddae4da15a47f9e5d=httpsavatar-management--avatars.us-west-2.prod.public.atl-paas.netinitialsCA-0.png"}}, "nickname": "caguero", "type": "user", "account_id": "557058:4ded1ddf-947e-4154-bbd1-3dba24f1bdbd"}, "inline": {"to": 206, "from": null, "outdated": false, "path": "vrx_gazebo/src/perception_scoring_plugin.cc"}, "updated_on": "2019-08-15T20:58:00.100515+00:00", "type": "pullrequest_comment", "id": 113309321}